GetGeneLength/GetGeneLength.py
GetGeneLength/__init__.py
GetGeneLength-0.0.4.dist-info/LICENSE
GetGeneLength-0.0.4.dist-info/METADATA
GetGeneLength-0.0.4.dist-info/WHEEL
GetGeneLength-0.0.4.dist-info/entry_points.txt
GetGeneLength-0.0.4.dist-info/top_level.txt
GetGeneLength-0.0.4.dist-info/RECORD
