Metadata-Version: 2.1
Name: GetGeneLength
Version: 0.0.4
Summary: Extract gene length based on featureCount calculation gene nonredundant exon length method.
Home-page: https://github.com/junjunlab/GetGeneLength
Author: laojunjun
Author-email: 3219030654@stu.cpu.edu.cn
License: UNKNOWN
Project-URL: Bug Tracker, https://github.com/junjunlab/GetGeneLength/issues
Platform: UNKNOWN
Classifier: Programming Language :: Python :: 3
Classifier: License :: OSI Approved :: MIT License
Classifier: Operating System :: OS Independent
Requires-Python: >=3.6
License-File: LICENSE
